condensetech/cdk_constructs/__init__.py
condensetech/cdk_constructs/py.typed
condensetech/cdk_constructs/_jsii/__init__.py
condensetech/cdk_constructs/_jsii/cdk-constructs@0.5.14.jsii.tgz
condensetech.cdk_constructs-0.5.14.dist-info/LICENSE
condensetech.cdk_constructs-0.5.14.dist-info/METADATA
condensetech.cdk_constructs-0.5.14.dist-info/WHEEL
condensetech.cdk_constructs-0.5.14.dist-info/top_level.txt
condensetech.cdk_constructs-0.5.14.dist-info/RECORD
